Workbook
Name Slicer_Branch: #N/A
Name Slicer_Customer_type: #N/A
Name Slicer_Payment: #N/A

Sheet Supermarket Sales 
A1: Date | B1: Branch | C1: Customer type | D1: Gender | E1: Product line | F1: Unit price | G1: Quantity | H1: Payment | I1: Rating | J1: Total sales | K1: Tax amount | L1: Rating Category | M1: =AVERAGE(I2:I5054) -> 6.8840293
A2: 45292 | B2: Brooklyn | C2: Member | D2: Female | E2: Food & Beverages | F2: 84.63 | G2: 10 | H2: Credit card | I2: 9 | J2: =F2*G2 -> 846.3 | K2: =J2*5% -> 42.315 | L2: {=_xlfn.IFS(I2>=9,"Good",I2>=6,"Average",I2<6,"Poor")} -> Good
A3: 45292 | B3: Queens | C3: Normal | D3: Female | E3: Electronics | F3: 63.22 | G3: 2 | H3: Cash | I3: 8.5 | J3: =F3*G3 -> 126.44 | K3: =J3*5% -> 6.322 | L3: {=_xlfn.IFS(I3>=9,"Good",I3>=6,"Average",I3<6,"Poor")} -> Average | N3: TAX
A4: 45292 | B4: Brooklyn | C4: Normal | D4: Female | E4: Electronics | F4: 74.71 | G4: 6 | H4: Cash | I4: 6.7 | J4: =F4*G4 -> 448.26 | K4: =J4*5% -> 22.413 | L4: {=_xlfn.IFS(I4>=9,"Good",I4>=6,"Average",I4<6,"Poor")} -> Average | N4: 0.05
A5: 45292 | B5: Queens | C5: Member | D5: Female | E5: Sports & Travel | F5: 36.98 | G5: 10 | H5: Credit card | I5: 7 | J5: =F5*G5 -> 369.8 | K5: =J5*5% -> 18.49 | L5: {=_xlfn.IFS(I5>=9,"Good",I5>=6,"Average",I5<6,"Poor")} -> Average
A6: 45292 | B6: Manhattan | C6: Member | D6: Female | E6: Sports & Travel | F6: 27.04 | G6: 4 | H6: Ewallet | I6: 6.9 | J6: =F6*G6 -> 108.16 | K6: =J6*5% -> 5.408 | L6: {=_xlfn.IFS(I6>=9,"Good",I6>=6,"Average",I6<6,"Poor")} -> Average
A7: 45292 | B7: Manhattan | C7: Normal | D7: Female | E7: Fashion & Accs | F7: 65.74 | G7: 9 | H7: Cash | I7: 7.7 | J7: =F7*G7 -> 591.66 | K7: =J7*5% -> 29.583 | L7: {=_xlfn.IFS(I7>=9,"Good",I7>=6,"Average",I7<6,"Poor")} -> Average
A8: 45292 | B8: Manhattan | C8: Member | D8: Male | E8: Home & Lifestyle | F8: 47.59 | G8: 8 | H8: Cash | I8: 5.7 | J8: =F8*G8 -> 380.72 | K8: =J8*5% -> 19.036 | L8: {=_xlfn.IFS(I8>=9,"Good",I8>=6,"Average",I8<6,"Poor")} -> Poor
A9: 45292 | B9: Manhattan | C9: Normal | D9: Male | E9: Sports & Travel | F9: 72.61 | G9: 6 | H9: Credit card | I9: 6.9 | J9: =F9*G9 -> 435.66 | K9: =J9*5% -> 21.783 | L9: {=_xlfn.IFS(I9>=9,"Good",I9>=6,"Average",I9<6,"Poor")} -> Average
A10: 45292 | B10: Queens | C10: Normal | D10: Male | E10: Health & Beauty | F10: 62.87 | G10: 2 | H10: Cash | I10: 5 | J10: =F10*G10 -> 125.74 | K10: =J10*5% -> 6.287 | L10: {=_xlfn.IFS(I10>=9,"Good",I10>=6,"Average",I10<6,"Poor")} -> Poor
A11: 45292 | B11: Brooklyn | C11: Normal | D11: Male | E11: Food & Beverages | F11: 21.12 | G11: 8 | H11: Cash | I11: 6.3 | J11: =F11*G11 -> 168.96 | K11: =J11*5% -> 8.448 | L11: {=_xlfn.IFS(I11>=9,"Good",I11>=6,"Average",I11<6,"Poor")} -> Average
A12: 45292 | B12: Queens | C12: Member | D12: Female | E12: Sports & Travel | F12: 29.22 | G12: 6 | H12: Ewallet | I12: 5 | J12: =F12*G12 -> 175.32 | K12: =J12*5% -> 8.766 | L12: {=_xlfn.IFS(I12>=9,"Good",I12>=6,"Average",I12<6,"Poor")} -> Poor
A13: 45292 | B13: Manhattan | C13: Member | D13: Female | E13: Electronics | F13: 74.22 | G13: 10 | H13: Credit card | I13: 4.3 | J13: =F13*G13 -> 742.2 | K13: =J13*5% -> 37.11 | L13: {=_xlfn.IFS(I13>=9,"Good",I13>=6,"Average",I13<6,"Poor")} -> Poor
A14: 45323 | B14: Manhattan | C14: Normal | D14: Male | E14: Sports & Travel | F14: 42.47 | G14: 1 | H14: Cash | I14: 5.7 | J14: =F14*G14 -> 42.47 | K14: =J14*5% -> 2.1235 | L14: {=_xlfn.IFS(I14>=9,"Good",I14>=6,"Average",I14<6,"Poor")} -> Poor
A15: 45323 | B15: Brooklyn | C15: Member | D15: Male | E15: Fashion & Accs | F15: 40.61 | G15: 9 | H15: Cash | I15: 7 | J15: =F15*G15 -> 365.49 | K15: =J15*5% -> 18.2745 | L15: {=_xlfn.IFS(I15>=9,"Good",I15>=6,"Average",I15<6,"Poor")} -> Average
A16: 45323 | B16: Brooklyn | C16: Normal | D16: Male | E16: Sports & Travel | F16: 44.63 | G16: 6 | H16: Credit card | I16: 5.1 | J16: =F16*G16 -> 267.78 | K16: =J16*5% -> 13.389 | L16: {=_xlfn.IFS(I16>=9,"Good",I16>=6,"Average",I16<6,"Poor")} -> Poor
... A119: 45627 | B119: Brooklyn | C119: Normal | D119: Female | E119: Home & Lifestyle | F119: 51.07 | G119: 7 | H119: Cash | I119: 7 | J119: =F119*G119 -> 357.49 | K119: =J119*5% -> 17.8745 | L119: {=_xlfn.IFS(I119>=9,"Good",I119>=6,"Average",I119<6,"Poor")} -> Average
A120: 1/13/2024 | B120: Brooklyn | C120: Member | D120: Male | E120: Sports & Travel | F120: 72.6 | G120: 6 | H120: Cash | I120: 6.9 | J120: =F120*G120 -> 435.6 | K120: =J120*5% -> 21.78 | L120: {=_xlfn.IFS(I120>=9,"Good",I120>=6,"Average",I120<6,"Poor")} -> Average
A121: 1/13/2024 | B121: Manhattan | C121: Member | D121: Male | E121: Home & Lifestyle | F121: 81.01 | G121: 3 | H121: Credit card | I121: 9.3 | J121: =F121*G121 -> 243.03 | K121: =J121*5% -> 12.1515 | L121: {=_xlfn.IFS(I121>=9,"Good",I121>=6,"Average",I121<6,"Poor")} -> Good
A122: 1/13/2024 | B122: Queens | C122: Member | D122: Female | E122: Fashion & Accs | F122: 74.29 | G122: 1 | H122: Cash | I122: 5 | J122: =F122*G122 -> 74.29 | K122: =J122*5% -> 3.7145 | L122: {=_xlfn.IFS(I122>=9,"Good",I122>=6,"Average",I122<6,"Poor")} -> Poor
A123: 1/13/2024 | B123: Manhattan | C123: Normal | D123: Female | E123: Electronics | F123: 23.46 | G123: 6 | H123: Ewallet | I123: 6.4 | J123: =F123*G123 -> 140.76 | K123: =J123*5% -> 7.038 | L123: {=_xlfn.IFS(I123>=9,"Good",I123>=6,"Average",I123<6,"Poor")} -> Average
A124: 1/13/2024 | B124: Manhattan | C124: Member | D124: Female | E124: Health & Beauty | F124: 39.62 | G124: 9 | H124: Credit card | I124: 6.8 | J124: =F124*G124 -> 356.58 | K124: =J124*5% -> 17.829 | L124: {=_xlfn.IFS(I124>=9,"Good",I124>=6,"Average",I124<6,"Poor")} -> Average
A125: 1/13/2024 | B125: Queens | C125: Member | D125: Female | E125: Food & Beverages | F125: 21.04 | G125: 4 | H125: Cash | I125: 7.6 | J125: =F125*G125 -> 84.16 | K125: =J125*5% -> 4.208 | L125: {=_xlfn.IFS(I125>=9,"Good",I125>=6,"Average",I125<6,"Poor")} -> Average
A126: 1/13/2024 | B126: Brooklyn | C126: Member | D126: Male | E126: Fashion & Accs | F126: 59.86 | G126: 2 | H126: Ewallet | I126: 6.7 | J126: =F126*G126 -> 119.72 | K126: =J126*5% -> 5.986 | L126: {=_xlfn.IFS(I126>=9,"Good",I126>=6,"Average",I126<6,"Poor")} -> Average
A127: 1/13/2024 | B127: Brooklyn | C127: Normal | D127: Male | E127: Food & Beverages | F127: 72.39 | G127: 2 | H127: Credit card | I127: 8.1 | J127: =F127*G127 -> 144.78 | K127: =J127*5% -> 7.239 | L127: {=_xlfn.IFS(I127>=9,"Good",I127>=6,"Average",I127<6,"Poor")} -> Average
A128: 1/13/2024 | B128: Manhattan | C128: Normal | D128: Male | E128: Sports & Travel | F128: 45.58 | G128: 7 | H128: Cash | I128: 5 | J128: =F128*G128 -> 319.06 | K128: =J128*5% -> 15.953 | L128: {=_xlfn.IFS(I128>=9,"Good",I128>=6,"Average",I128<6,"Poor")} -> Poor
A129: 1/13/2024 | B129: Queens | C129: Normal | D129: Female | E129: Electronics | F129: 41.65 | G129: 10 | H129: Credit card | I129: 5.4 | J129: =F129*G129 -> 416.5 | K129: =J129*5% -> 20.825 | L129: {=_xlfn.IFS(I129>=9,"Good",I129>=6,"Average",I129<6,"Poor")} -> Poor
A130: 1/14/2024 | B130: Queens | C130: Member | D130: Male | E130: Health & Beauty | F130: 60.47 | G130: 3 | H130: Credit card | I130: 5.6 | J130: =F130*G130 -> 181.41 | K130: =J130*5% -> 9.0705 | L130: {=_xlfn.IFS(I130>=9,"Good",I130>=6,"Average",I130<6,"Poor")} -> Poor
A131: 1/14/2024 | B131: Brooklyn | C131: Normal | D131: Female | E131: Sports & Travel | F131: 34.81 | G131: 1 | H131: Credit card | I131: 7 | J131: =F131*G131 -> 34.81 | K131: =J131*5% -> 1.7405 | L131: {=_xlfn.IFS(I131>=9,"Good",I131>=6,"Average",I131<6,"Poor")} -> Average
... A353: 1/31/2024 | B353: Manhattan | C353: Member | D353: Male | E353: Electronics | F353: 66.35 | G353: 1 | H353: Credit card | I353: 9.7 | J353: =F353*G353 -> 66.35 | K353: =J353*5% -> 3.3175 | L353: {=_xlfn.IFS(I353>=9,"Good",I353>=6,"Average",I353<6,"Poor")} -> Good
A354: 45293 | B354: Queens | C354: Member | D354: Female | E354: Food & Beverages | F354: 87.48 | G354: 6 | H354: Ewallet | I354: 5.1 | J354: =F354*G354 -> 524.88 | K354: =J354*5% -> 26.244 | L354: {=_xlfn.IFS(I354>=9,"Good",I354>=6,"Average",I354<6,"Poor")} -> Poor
A355: 45293 | B355: Manhattan | C355: Member | D355: Female | E355: Food & Beverages | F355: 14.23 | G355: 5 | H355: Credit card | I355: 4.4 | J355: =F355*G355 -> 71.15 | K355: =J355*5% -> 3.5575 | L355: {=_xlfn.IFS(I355>=9,"Good",I355>=6,"Average",I355<6,"Poor")} -> Poor
A356: 45293 | B356: Manhattan | C356: Member | D356: Male | E356: Sports & Travel | F356: 69.52 | G356: 7 | H356: Credit card | I356: 8.5 | J356: =F356*G356 -> 486.64 | K356: =J356*5% -> 24.332 | L356: {=_xlfn.IFS(I356>=9,"Good",I356>=6,"Average",I356<6,"Poor")} -> Average
A357: 45293 | B357: Queens | C357: Normal | D357: Female | E357: Electronics | F357: 23.07 | G357: 9 | H357: Cash | I357: 4.9 | J357: =F357*G357 -> 207.63 | K357: =J357*5% -> 10.3815 | L357: {=_xlfn.IFS(I357>=9,"Good",I357>=6,"Average",I357<6,"Poor")} -> Poor
A358: 45293 | B358: Queens | C358: Member | D358: Female | E358: Home & Lifestyle | F358: 80.79 | G358: 9 | H358: Credit card | I358: 9.5 | J358: =F358*G358 -> 727.11 | K358: =J358*5% -> 36.3555 | L358: {=_xlfn.IFS(I358>=9,"Good",I358>=6,"Average",I358<6,"Poor")} -> Good
A359: 45293 | B359: Manhattan | C359: Member | D359: Female | E359: Health & Beauty | F359: 77.68 | G359: 4 | H359: Cash | I359: 8.4 | J359: =F359*G359 -> 310.72 | K359: =J359*5% -> 15.536 | L359: {=_xlfn.IFS(I359>=9,"Good",I359>=6,"Average",I359<6,"Poor")} -> Average
A360: 45324 | B360: Brooklyn | C360: Member | D360: Female | E360: Electronics | F360: 26.26 | G360: 7 | H360: Cash | I360: 9.9 | J360: =F360*G360 -> 183.82 | K360: =J360*5% -> 9.191 | L360: {=_xlfn.IFS(I360>=9,"Good",I360>=6,"Average",I360<6,"Poor")} -> Good
A361: 45324 | B361: Manhattan | C361: Member | D361: Male | E361: Fashion & Accs | F361: 43.13 | G361: 10 | H361: Credit card | I361: 5.5 | J361: =F361*G361 -> 431.3 | K361: =J361*5% -> 21.565 | L361: {=_xlfn.IFS(I361>=9,"Good",I361>=6,"Average",I361<6,"Poor")} -> Poor
A362: 45324 | B362: Brooklyn | C362: Normal | D362: Female | E362: Fashion & Accs | F362: 25.56 | G362: 7 | H362: Cash | I362: 7.1 | J362: =F362*G362 -> 178.92 | K362: =J362*5% -> 8.946 | L362: {=_xlfn.IFS(I362>=9,"Good",I362>=6,"Average",I362<6,"Poor")} -> Average
A363: 45324 | B363: Queens | C363: Member | D363: Female | E363: Food & Beverages | F363: 38.42 | G363: 1 | H363: Cash | I363: 8.6 | J363: =F363*G363 -> 38.42 | K363: =J363*5% -> 1.921 | L363: {=_xlfn.IFS(I363>=9,"Good",I363>=6,"Average",I363<6,"Poor")} -> Average
A364: 45324 | B364: Queens | C364: Normal | D364: Male | E364: Food & Beverages | F364: 65.97 | G364: 8 | H364: Cash | I364: 8.4 | J364: =F364*G364 -> 527.76 | K364: =J364*5% -> 26.388 | L364: {=_xlfn.IFS(I364>=9,"Good",I364>=6,"Average",I364<6,"Poor")} -> Average
A365: 45324 | B365: Manhattan | C365: Member | D365: Female | E365: Sports & Travel | F365: 51.52 | G365: 8 | H365: Cash | I365: 9.6 | J365: =F365*G365 -> 412.16 | K365: =J365*5% -> 20.608 | L365: {=_xlfn.IFS(I365>=9,"Good",I365>=6,"Average",I365<6,"Poor")} -> Good
... A495: 45628 | B495: Manhattan | C495: Member | D495: Female | E495: Sports & Travel | F495: 71.63 | G495: 2 | H495: Ewallet | I495: 8.8 | J495: =F495*G495 -> 143.26 | K495: =J495*5% -> 7.163 | L495: {=_xlfn.IFS(I495>=9,"Good",I495>=6,"Average",I495<6,"Poor")} -> Average
A496: 2/13/2024 | B496: Manhattan | C496: Member | D496: Male | E496: Electronics | F496: 76.82 | G496: 1 | H496: Ewallet | I496: 7.2 | J496: =F496*G496 -> 76.82 | K496: =J496*5% -> 3.841 | L496: {=_xlfn.IFS(I496>=9,"Good",I496>=6,"Average",I496<6,"Poor")} -> Average
A497: 2/13/2024 | B497: Brooklyn | C497: Member | D497: Female | E497: Sports & Travel | F497: 20.18 | G497: 4 | H497: Credit card | I497: 5 | J497: =F497*G497 -> 80.72 | K497: =J497*5% -> 4.036 | L497: {=_xlfn.IFS(I497>=9,"Good",I497>=6,"Average",I497<6,"Poor")} -> Poor
A498: 2/13/2024 | B498: Queens | C498: Member | D498: Female | E498: Fashion & Accs | F498: 92.98 | G498: 2 | H498: Credit card | I498: 8 | J498: =F498*G498 -> 185.96 | K498: =J498*5% -> 9.298 | L498: {=_xlfn.IFS(I498>=9,"Good",I498>=6,"Average",I498<6,"Poor")} -> Average
A499: 2/13/2024 | B499: Brooklyn | C499: Member | D499: Female | E499: Fashion & Accs | F499: 29.56 | G499: 5 | H499: Cash | I499: 6.9 | J499: =F499*G499 -> 147.8 | K499: =J499*5% -> 7.39 | L499: {=_xlfn.IFS(I499>=9,"Good",I499>=6,"Average",I499<6,"Poor")} -> Average
A500: 2/13/2024 | B500: Queens | C500: Normal | D500: Female | E500: Fashion & Accs | F500: 22.51 | G500: 7 | H500: Credit card | I500: 4.8 | J500: =F500*G500 -> 157.57 | K500: =J500*5% -> 7.8785 | L500: {=_xlfn.IFS(I500>=9,"Good",I500>=6,"Average",I500<6,"Poor")} -> Poor
A501: 2/13/2024 | B501: Queens | C501: Member | D501: Female | E501: Food & Beverages | F501: 14.87 | G501: 2 | H501: Credit card | I501: 8.9 | J501: =F501*G501 -> 29.74 | K501: =J501*5% -> 1.487 | L501: {=_xlfn.IFS(I501>=9,"Good",I501>=6,"Average",I501<6,"Poor")} -> Average
A502: 2/13/2024 | B502: Manhattan | C502: Member | D502: Male | E502: Electronics | F502: 32.25 | G502: 4 | H502: Ewallet | I502: 6.5 | J502: =F502*G502 -> 129 | K502: =J502*5% -> 6.45 | L502: {=_xlfn.IFS(I502>=9,"Good",I502>=6,"Average",I502<6,"Poor")} -> Average
A503: 2/13/2024 | B503: Brooklyn | C503: Normal | D503: Male | E503: Sports & Travel | F503: 13.69 | G503: 6 | H503: Cash | I503: 6.3 | J503: =F503*G503 -> 82.14 | K503: =J503*5% -> 4.107 | L503: {=_xlfn.IFS(I503>=9,"Good",I503>=6,"Average",I503<6,"Poor")} -> Average
A504: 2/14/2024 | B504: Manhattan | C504: Member | D504: Male | E504: Health & Beauty | F504: 91.3 | G504: 1 | H504: Ewallet | I504: 9.2 | J504: =F504*G504 -> 91.3 | K504: =J504*5% -> 4.565 | L504: {=_xlfn.IFS(I504>=9,"Good",I504>=6,"Average",I504<6,"Poor")} -> Good
A505: 2/14/2024 | B505: Manhattan | C505: Normal | D505: Male | E505: Sports & Travel | F505: 44.65 | G505: 3 | H505: Cash | I505: 6.2 | J505: =F505*G505 -> 133.95 | K505: =J505*5% -> 6.6975 | L505: {=_xlfn.IFS(I505>=9,"Good",I505>=6,"Average",I505<6,"Poor")} -> Average
A506: 2/14/2024 | B506: Brooklyn | C506: Member | D506: Male | E506: Health & Beauty | F506: 75.74 | G506: 4 | H506: Cash | I506: 7.6 | J506: =F506*G506 -> 302.96 | K506: =J506*5% -> 15.148 | L506: {=_xlfn.IFS(I506>=9,"Good",I506>=6,"Average",I506<6,"Poor")} -> Average
A507: 2/14/2024 | B507: Brooklyn | C507: Member | D507: Female | E507: Sports & Travel | F507: 60.08 | G507: 7 | H507: Credit card | I507: 4.5 | J507: =F507*G507 -> 420.56 | K507: =J507*5% -> 21.028 | L507: {=_xlfn.IFS(I507>=9,"Good",I507>=6,"Average",I507<6,"Poor")} -> Poor
... A664: 2/29/2024 | B664: Manhattan | C664: Member | D664: Female | E664: Health & Beauty | F664: 10.16 | G664: 5 | H664: Ewallet | I664: 4.1 | J664: =F664*G664 -> 50.8 | K664: =J664*5% -> 2.54 | L664: {=_xlfn.IFS(I664>=9,"Good",I664>=6,"Average",I664<6,"Poor")} -> Poor
A665: 45294 | B665: Brooklyn | C665: Normal | D665: Male | E665: Electronics | F665: 27.5 | G665: 3 | H665: Ewallet | I665: 6.5 | J665: =F665*G665 -> 82.5 | K665: =J665*5% -> 4.125 | L665: {=_xlfn.IFS(I665>=9,"Good",I665>=6,"Average",I665<6,"Poor")} -> Average
A666: 45294 | B666: Queens | C666: Member | D666: Female | E666: Food & Beverages | F666: 74.89 | G666: 4 | H666: Ewallet | I666: 4.2 | J666: =F666*G666 -> 299.56 | K666: =J666*5% -> 14.978 | L666: {=_xlfn.IFS(I666>=9,"Good",I666>=6,"Average",I666<6,"Poor")} -> Poor
A667: 45294 | B667: Manhattan | C667: Normal | D667: Female | E667: Electronics | F667: 45.48 | G667: 10 | H667: Credit card | I667: 4.8 | J667: =F667*G667 -> 454.8 | K667: =J667*5% -> 22.74 | L667: {=_xlfn.IFS(I667>=9,"Good",I667>=6,"Average",I667<6,"Poor")} -> Poor
A668: 45294 | B668: Brooklyn | C668: Member | D668: Male | E668: Food & Beverages | F668: 53.72 | G668: 1 | H668: Ewallet | I668: 6.4 | J668: =F668*G668 -> 53.72 | K668: =J668*5% -> 2.686 | L668: {=_xlfn.IFS(I668>=9,"Good",I668>=6,"Average",I668<6,"Poor")} -> Average
A669: 45294 | B669: Brooklyn | C669: Member | D669: Male | E669: Fashion & Accs | F669: 81.31 | G669: 7 | H669: Ewallet | I669: 6.3 | J669: =F669*G669 -> 569.17 | K669: =J669*5% -> 28.4585 | L669: {=_xlfn.IFS(I669>=9,"Good",I669>=6,"Average",I669<6,"Poor")} -> Average
A670: 45294 | B670: Manhattan | C670: Normal | D670: Male | E670: Home & Lifestyle | F670: 34.73 | G670: 2 | H670: Ewallet | I670: 9.7 | J670: =F670*G670 -> 69.46 | K670: =J670*5% -> 3.473 | L670: {=_xlfn.IFS(I670>=9,"Good",I670>=6,"Average",I670<6,"Poor")} -> Good
A671: 45294 | B671: Queens | C671: Normal | D671: Male | E671: Fashion & Accs | F671: 78.55 | G671: 9 | H671: Cash | I671: 7.2 | J671: =F671*G671 -> 706.95 | K671: =J671*5% -> 35.3475 | L671: {=_xlfn.IFS(I671>=9,"Good",I671>=6,"Average",I671<6,"Poor")} -> Average
A672: 45294 | B672: Manhattan | C672: Member | D672: Female | E672: Fashion & Accs | F672: 22.32 | G672: 4 | H672: Credit card | I672: 4.4 | J672: =F672*G672 -> 89.28 | K672: =J672*5% -> 4.464 | L672: {=_xlfn.IFS(I672>=9,"Good",I672>=6,"Average",I672<6,"Poor")} -> Poor
A673: 45294 | B673: Brooklyn | C673: Normal | D673: Male | E673: Health & Beauty | F673: 69.51 | G673: 2 | H673: Ewallet | I673: 8.1 | J673: =F673*G673 -> 139.02 | K673: =J673*5% -> 6.951 | L673: {=_xlfn.IFS(I673>=9,"Good",I673>=6,"Average",I673<6,"Poor")} -> Average
A674: 45294 | B674: Brooklyn | C674: Normal | D674: Male | E674: Health & Beauty | F674: 14.82 | G674: 3 | H674: Credit card | I674: 8.7 | J674: =F674*G674 -> 44.46 | K674: =J674*5% -> 2.223 | L674: {=_xlfn.IFS(I674>=9,"Good",I674>=6,"Average",I674<6,"Poor")} -> Average
A675: 45325 | B675: Brooklyn | C675: Member | D675: Female | E675: Electronics | F675: 26.26 | G675: 3 | H675: Ewallet | I675: 6.3 | J675: =F675*G675 -> 78.78 | K675: =J675*5% -> 3.939 | L675: {=_xlfn.IFS(I675>=9,"Good",I675>=6,"Average",I675<6,"Poor")} -> Average
A676: 45325 | B676: Queens | C676: Member | D676: Female | E676: Sports & Travel | F676: 54.55 | G676: 10 | H676: Credit card | I676: 7.1 | J676: =F676*G676 -> 545.5 | K676: =J676*5% -> 27.275 | L676: {=_xlfn.IFS(I676>=9,"Good",I676>=6,"Average",I676<6,"Poor")} -> Average
... A817: 45629 | B817: Brooklyn | C817: Member | D817: Male | E817: Health & Beauty | F817: 39.01 | G817: 1 | H817: Credit card | I817: 4.7 | J817: =F817*G817 -> 39.01 | K817: =J817*5% -> 1.9505 | L817: {=_xlfn.IFS(I817>=9,"Good",I817>=6,"Average",I817<6,"Poor")} -> Poor
A818: 3/13/2024 | B818: Queens | C818: Normal | D818: Male | E818: Fashion & Accs | F818: 56.5 | G818: 1 | H818: Ewallet | I818: 9.6 | J818: =F818*G818 -> 56.5 | K818: =J818*5% -> 2.825 | L818: {=_xlfn.IFS(I818>=9,"Good",I818>=6,"Average",I818<6,"Poor")} -> Good
A819: 3/13/2024 | B819: Manhattan | C819: Normal | D819: Female | E819: Food & Beverages | F819: 54.27 | G819: 5 | H819: Ewallet | I819: 4.6 | J819: =F819*G819 -> 271.35 | K819: =J819*5% -> 13.5675 | L819: {=_xlfn.IFS(I819>=9,"Good",I819>=6,"Average",I819<6,"Poor")} -> Poor
A820: 3/13/2024 | B820: Brooklyn | C820: Member | D820: Female | E820: Fashion & Accs | F820: 38.3 | G820: 4 | H820: Cash | I820: 5.7 | J820: =F820*G820 -> 153.2 | K820: =J820*5% -> 7.66 | L820: {=_xlfn.IFS(I820>=9,"Good",I820>=6,"Average",I820<6,"Poor")} -> Poor
A821: 3/13/2024 | B821: Manhattan | C821: Member | D821: Male | E821: Health & Beauty | F821: 15.87 | G821: 10 | H821: Cash | I821: 5.8 | J821: =F821*G821 -> 158.7 | K821: =J821*5% -> 7.935 | L821: {=_xlfn.IFS(I821>=9,"Good",I821>=6,"Average",I821<6,"Poor")} -> Poor
A822: 3/13/2024 | B822: Manhattan | C822: Normal | D822: Male | E822: Food & Beverages | F822: 45.79 | G822: 7 | H822: Credit card | I822: 7 | J822: =F822*G822 -> 320.53 | K822: =J822*5% -> 16.0265 | L822: {=_xlfn.IFS(I822>=9,"Good",I822>=6,"Average",I822<6,"Poor")} -> Average
A823: 3/13/2024 | B823: Queens | C823: Member | D823: Male | E823: Sports & Travel | F823: 72.88 | G823: 2 | H823: Cash | I823: 6.1 | J823: =F823*G823 -> 145.76 | K823: =J823*5% -> 7.288 | L823: {=_xlfn.IFS(I823>=9,"Good",I823>=6,"Average",I823<6,"Poor")} -> Average
A824: 3/13/2024 | B824: Brooklyn | C824: Normal | D824: Male | E824: Health & Beauty | F824: 18.11 | G824: 10 | H824: Ewallet | I824: 5.9 | J824: =F824*G824 -> 181.1 | K824: =J824*5% -> 9.055 | L824: {=_xlfn.IFS(I824>=9,"Good",I824>=6,"Average",I824<6,"Poor")} -> Poor
A825: 3/13/2024 | B825: Brooklyn | C825: Normal | D825: Female | E825: Fashion & Accs | F825: 34.7 | G825: 2 | H825: Ewallet | I825: 8.2 | J825: =F825*G825 -> 69.4 | K825: =J825*5% -> 3.47 | L825: {=_xlfn.IFS(I825>=9,"Good",I825>=6,"Average",I825<6,"Poor")} -> Average
A826: 3/13/2024 | B826: Queens | C826: Member | D826: Male | E826: Home & Lifestyle | F826: 63.91 | G826: 8 | H826: Credit card | I826: 4.6 | J826: =F826*G826 -> 511.28 | K826: =J826*5% -> 25.564 | L826: {=_xlfn.IFS(I826>=9,"Good",I826>=6,"Average",I826<6,"Poor")} -> Poor
A827: 3/13/2024 | B827: Queens | C827: Normal | D827: Female | E827: Fashion & Accs | F827: 12.19 | G827: 8 | H827: Ewallet | I827: 6.8 | J827: =F827*G827 -> 97.52 | K827: =J827*5% -> 4.876 | L827: {=_xlfn.IFS(I827>=9,"Good",I827>=6,"Average",I827<6,"Poor")} -> Average
A828: 3/14/2024 | B828: Queens | C828: Normal | D828: Female | E828: Electronics | F828: 51.32 | G828: 9 | H828: Cash | I828: 5.6 | J828: =F828*G828 -> 461.88 | K828: =J828*5% -> 23.094 | L828: {=_xlfn.IFS(I828>=9,"Good",I828>=6,"Average",I828<6,"Poor")} -> Poor
A829: 3/14/2024 | B829: Queens | C829: Member | D829: Male | E829: Sports & Travel | F829: 42.85 | G829: 1 | H829: Credit card | I829: 9.3 | J829: =F829*G829 -> 42.85 | K829: =J829*5% -> 2.1425 | L829: {=_xlfn.IFS(I829>=9,"Good",I829>=6,"Average",I829<6,"Poor")} -> Good
... A1009: 3/30/2024 | B1009: Queens | C1009: Normal | D1009: Male | E1009: Health & Beauty | F1009: 70.21 | G1009: 6 | H1009: Cash | I1009: 7.4 | J1009: =F1009*G1009 -> 421.26 | K1009: =J1009*5% -> 21.063 | L1009: {=_xlfn.IFS(I1009>=9,"Good",I1009>=6,"Average",I1009<6,"Poor")} -> Average
A1010: 45295 | B1010: Queens | C1010: Member | D1010: Male | E1010: Electronics | F1010: 37.06 | G1010: 4 | H1010: Ewallet | I1010: 9.7 | J1010: =F1010*G1010 -> 148.24 | K1010: =J1010*5% -> 7.412 | L1010: {=_xlfn.IFS(I1010>=9,"Good",I1010>=6,"Average",I1010<6,"Poor")} -> Good
A1011: 45295 | B1011: Brooklyn | C1011: Member | D1011: Male | E1011: Electronics | F1011: 87.87 | G1011: 9 | H1011: Ewallet | I1011: 5.6 | J1011: =F1011*G1011 -> 790.83 | K1011: =J1011*5% -> 39.5415 | L1011: {=_xlfn.IFS(I1011>=9,"Good",I1011>=6,"Average",I1011<6,"Poor")} -> Poor
A1012: 45295 | B1012: Brooklyn | C1012: Normal | D1012: Male | E1012: Electronics | F1012: 45.35 | G1012: 6 | H1012: Ewallet | I1012: 6.1 | J1012: =F1012*G1012 -> 272.1 | K1012: =J1012*5% -> 13.605 | L1012: {=_xlfn.IFS(I1012>=9,"Good",I1012>=6,"Average",I1012<6,"Poor")} -> Average
A1013: 45295 | B1013: Manhattan | C1013: Member | D1013: Male | E1013: Electronics | F1013: 66.35 | G1013: 1 | H1013: Credit card | I1013: 9.7 | J1013: =F1013*G1013 -> 66.35 | K1013: =J1013*5% -> 3.3175 | L1013: {=_xlfn.IFS(I1013>=9,"Good",I1013>=6,"Average",I1013<6,"Poor")} -> Good
A1014: 45295 | B1014: Queens | C1014: Member | D1014: Female | E1014: Food & Beverages | F1014: 87.48 | G1014: 6 | H1014: Ewallet | I1014: 5.1 | J1014: =F1014*G1014 -> 524.88 | K1014: =J1014*5% -> 26.244 | L1014: {=_xlfn.IFS(I1014>=9,"Good",I1014>=6,"Average",I1014<6,"Poor")} -> Poor
A1015: 45295 | B1015: Manhattan | C1015: Member | D1015: Female | E1015: Food & Beverages | F1015: 14.23 | G1015: 5 | H1015: Credit card | I1015: 4.4 | J1015: =F1015*G1015 -> 71.15 | K1015: =J1015*5% -> 3.5575 | L1015: {=_xlfn.IFS(I1015>=9,"Good",I1015>=6,"Average",I1015<6,"Poor")} -> Poor
A1016: 45295 | B1016: Queens | C1016: Normal | D1016: Female | E1016: Electronics | F1016: 23.07 | G1016: 9 | H1016: Cash | I1016: 4.9 | J1016: =F1016*G1016 -> 207.63 | K1016: =J1016*5% -> 10.3815 | L1016: {=_xlfn.IFS(I1016>=9,"Good",I1016>=6,"Average",I1016<6,"Poor")} -> Poor
A1017: 45295 | B1017: Queens | C1017: Member | D1017: Female | E1017: Home & Lifestyle | F1017: 80.79 | G1017: 9 | H1017: Credit card | I1017: 9.5 | J1017: =F1017*G1017 -> 727.11 | K1017: =J1017*5% -> 36.3555 | L1017: {=_xlfn.IFS(I1017>=9,"Good",I1017>=6,"Average",I1017<6,"Poor")} -> Good
A1018: 45295 | B1018: Brooklyn | C1018: Member | D1018: Female | E1018: Electronics | F1018: 26.26 | G1018: 7 | H1018: Cash | I1018: 9.9 | J1018: =F1018*G1018 -> 183.82 | K1018: =J1018*5% -> 9.191 | L1018: {=_xlfn.IFS(I1018>=9,"Good",I1018>=6,"Average",I1018<6,"Poor")} -> Good
A1019: 45295 | B1019: Queens | C1019: Normal | D1019: Female | E1019: Fashion & Accs | F1019: 62.18 | G1019: 10 | H1019: Ewallet | I1019: 6 | J1019: =F1019*G1019 -> 621.8 | K1019: =J1019*5% -> 31.09 | L1019: {=_xlfn.IFS(I1019>=9,"Good",I1019>=6,"Average",I1019<6,"Poor")} -> Average
A1020: 45295 | B1020: Brooklyn | C1020: Normal | D1020: Male | E1020: Fashion & Accs | F1020: 69.08 | G1020: 2 | H1020: Credit card | I1020: 6.9 | J1020: =F1020*G1020 -> 138.16 | K1020: =J1020*5% -> 6.908 | L1020: {=_xlfn.IFS(I1020>=9,"Good",I1020>=6,"Average",I1020<6,"Poor")} -> Average
A1021: 45295 | B1021: Manhattan | C1021: Member | D1021: Female | E1021: Health & Beauty | F1021: 77.68 | G1021: 4 | H1021: Cash | I1021: 8.4 | J1021: =F1021*G1021 -> 310.72 | K1021: =J1021*5% -> 15.536 | L1021: {=_xlfn.IFS(I1021>=9,"Good",I1021>=6,"Average",I1021<6,"Poor")} -> Average
... A1242: 45630 | B1242: Queens | C1242: Normal | D1242: Male | E1242: Health & Beauty | F1242: 70.21 | G1242: 6 | H1242: Cash | I1242: 7.4 | J1242: =F1242*G1242 -> 421.26 | K1242: =J1242*5% -> 21.063 | L1242: {=_xlfn.IFS(I1242>=9,"Good",I1242>=6,"Average",I1242<6,"Poor")} -> Average
A1243: 4/13/2024 | B1243: Brooklyn | C1243: Normal | D1243: Male | E1243: Fashion & Accs | F1243: 69.08 | G1243: 2 | H1243: Credit card | I1243: 6.9 | J1243: =F1243*G1243 -> 138.16 | K1243: =J1243*5% -> 6.908 | L1243: {=_xlfn.IFS(I1243>=9,"Good",I1243>=6,"Average",I1243<6,"Poor")} -> Average
A1244: 4/13/2024 | B1244: Brooklyn | C1244: Normal | D1244: Male | E1244: Electronics | F1244: 45.35 | G1244: 6 | H1244: Ewallet | I1244: 6.1 | J1244: =F1244*G1244 -> 272.1 | K1244: =J1244*5% -> 13.605 | L1244: {=_xlfn.IFS(I1244>=9,"Good",I1244>=6,"Average",I1244<6,"Poor")} -> Average
A1245: 4/13/2024 | B1245: Manhattan | C1245: Member | D1245: Male | E1245: Electronics | F1245: 66.35 | G1245: 1 | H1245: Credit card | I1245: 9.7 | J1245: =F1245*G1245 -> 66.35 | K1245: =J1245*5% -> 3.3175 | L1245: {=_xlfn.IFS(I1245>=9,"Good",I1245>=6,"Average",I1245<6,"Poor")} -> Good
A1246: 4/13/2024 | B1246: Queens | C1246: Member | D1246: Female | E1246: Food & Beverages | F1246: 87.48 | G1246: 6 | H1246: Ewallet | I1246: 5.1 | J1246: =F1246*G1246 -> 524.88 | K1246: =J1246*5% -> 26.244 | L1246: {=_xlfn.IFS(I1246>=9,"Good",I1246>=6,"Average",I1246<6,"Poor")} -> Poor
A1247: 4/13/2024 | B1247: Manhattan | C1247: Member | D1247: Female | E1247: Food & Beverages | F1247: 14.23 | G1247: 5 | H1247: Credit card | I1247: 4.4 | J1247: =F1247*G1247 -> 71.15 | K1247: =J1247*5% -> 3.5575 | L1247: {=_xlfn.IFS(I1247>=9,"Good",I1247>=6,"Average",I1247<6,"Poor")} -> Poor
...

Sheet Clean Data
A1: Date | B1: Branch | C1: Customer type | D1: Gender | E1: Product line | F1: Unit price | G1: Quantity | H1: Payment | I1: Rating | J1: Total sales | K1: Tax amount | L1: Rating Category
A2: 45292 | B2: Brooklyn | C2: Member | D2: Female | E2: Food & Beverages | F2: 84.63 | G2: 10 | H2: Credit card | I2: 9 | J2: 846.3 | K2: 42.315 | L2: Good
A3: 45292 | B3: Queens | C3: Normal | D3: Female | E3: Electronics | F3: 63.22 | G3: 2 | H3: Cash | I3: 8.5 | J3: 126.44 | K3: 6.322 | L3: Good | N3: =AVERAGE(Table2_1[Rating]) -> 6.8840293
A4: 45292 | B4: Brooklyn | C4: Normal | D4: Female | E4: Electronics | F4: 74.71 | G4: 6 | H4: Cash | I4: 6.7 | J4: 448.26 | K4: 22.413 | L4: Average
A5: 45292 | B5: Queens | C5: Member | D5: Female | E5: Sports & Travel | F5: 36.98 | G5: 10 | H5: Credit card | I5: 7 | J5: 369.8 | K5: 18.49 | L5: Average
A6: 45292 | B6: Manhattan | C6: Member | D6: Female | E6: Sports & Travel | F6: 27.04 | G6: 4 | H6: Ewallet | I6: 6.9 | J6: 108.16 | K6: 5.408 | L6: Average
A7: 45292 | B7: Manhattan | C7: Normal | D7: Female | E7: Fashion & Accs | F7: 65.74 | G7: 9 | H7: Cash | I7: 7.7 | J7: 591.66 | K7: 29.583 | L7: Average
A8: 45292 | B8: Manhattan | C8: Member | D8: Male | E8: Home & Lifestyle | F8: 47.59 | G8: 8 | H8: Cash | I8: 5.7 | J8: 380.72 | K8: 19.036 | L8: Poor
A9: 45292 | B9: Manhattan | C9: Normal | D9: Male | E9: Sports & Travel | F9: 72.61 | G9: 6 | H9: Credit card | I9: 6.9 | J9: 435.66 | K9: 21.783 | L9: Average
A10: 45292 | B10: Queens | C10: Normal | D10: Male | E10: Health & Beauty | F10: 62.87 | G10: 2 | H10: Cash | I10: 5 | J10: 125.74 | K10: 6.287 | L10: Poor
A11: 45292 | B11: Brooklyn | C11: Normal | D11: Male | E11: Food & Beverages | F11: 21.12 | G11: 8 | H11: Cash | I11: 6.3 | J11: 168.96 | K11: 8.448 | L11: Average
A12: 45292 | B12: Queens | C12: Member | D12: Female | E12: Sports & Travel | F12: 29.22 | G12: 6 | H12: Ewallet | I12: 5 | J12: 175.32 | K12: 8.766 | L12: Poor
A13: 45292 | B13: Manhattan | C13: Member | D13: Female | E13: Electronics | F13: 74.22 | G13: 10 | H13: Credit card | I13: 4.3 | J13: 742.2 | K13: 37.11 | L13: Poor
A14: 45323 | B14: Manhattan | C14: Normal | D14: Male | E14: Sports & Travel | F14: 42.47 | G14: 1 | H14: Cash | I14: 5.7 | J14: 42.47 | K14: 2.1235 | L14: Poor
A15: 45323 | B15: Brooklyn | C15: Member | D15: Male | E15: Fashion & Accs | F15: 40.61 | G15: 9 | H15: Cash | I15: 7 | J15: 365.49 | K15: 18.2745 | L15: Average
... A119: 45627 | B119: Brooklyn | C119: Normal | D119: Female | E119: Home & Lifestyle | F119: 51.07 | G119: 7 | H119: Cash | I119: 7 | J119: 357.49 | K119: 17.8745 | L119: Average
B120: Brooklyn | C120: Member | D120: Male | E120: Sports & Travel | F120: 72.6 | G120: 6 | H120: Cash | I120: 6.9 | J120: 435.6 | K120: 21.78 | L120: Average
B121: Manhattan | C121: Member | D121: Male | E121: Home & Lifestyle | F121: 81.01 | G121: 3 | H121: Credit card | I121: 9.3 | J121: 243.03 | K121: 12.1515 | L121: Good
B122: Queens | C122: Member | D122: Female | E122: Fashion & Accs | F122: 74.29 | G122: 1 | H122: Cash | I122: 5 | J122: 74.29 | K122: 3.7145 | L122: Poor
B123: Manhattan | C123: Normal | D123: Female | E123: Electronics | F123: 23.46 | G123: 6 | H123: Ewallet | I123: 6.4 | J123: 140.76 | K123: 7.038 | L123: Average
B124: Manhattan | C124: Member | D124: Female | E124: Health & Beauty | F124: 39.62 | G124: 9 | H124: Credit card | I124: 6.8 | J124: 356.58 | K124: 17.829 | L124: Average
B125: Queens | C125: Member | D125: Female | E125: Food & Beverages | F125: 21.04 | G125: 4 | H125: Cash | I125: 7.6 | J125: 84.16 | K125: 4.208 | L125: Average
B126: Brooklyn | C126: Member | D126: Male | E126: Fashion & Accs | F126: 59.86 | G126: 2 | H126: Ewallet | I126: 6.7 | J126: 119.72 | K126: 5.986 | L126: Average
B127: Brooklyn | C127: Normal | D127: Male | E127: Food & Beverages | F127: 72.39 | G127: 2 | H127: Credit card | I127: 8.1 | J127: 144.78 | K127: 7.239 | L127: Good
B128: Manhattan | C128: Normal | D128: Male | E128: Sports & Travel | F128: 45.58 | G128: 7 | H128: Cash | I128: 5 | J128: 319.06 | K128: 15.953 | L128: Poor
B129: Queens | C129: Normal | D129: Female | E129: Electronics | F129: 41.65 | G129: 10 | H129: Credit card | I129: 5.4 | J129: 416.5 | K129: 20.825 | L129: Poor
B130: Queens | C130: Member | D130: Male | E130: Health & Beauty | F130: 60.47 | G130: 3 | H130: Credit card | I130: 5.6 | J130: 181.41 | K130: 9.0705 | L130: Poor
B131: Brooklyn | C131: Normal | D131: Female | E131: Sports & Travel | F131: 34.81 | G131: 1 | H131: Credit card | I131: 7 | J131: 34.81 | K131: 1.7405 | L131: Average
... B353: Manhattan | C353: Member | D353: Male | E353: Electronics | F353: 66.35 | G353: 1 | H353: Credit card | I353: 9.7 | J353: 66.35 | K353: 3.3175 | L353: Good
A354: 45293 | B354: Queens | C354: Member | D354: Female | E354: Food & Beverages | F354: 87.48 | G354: 6 | H354: Ewallet | I354: 5.1 | J354: 524.88 | K354: 26.244 | L354: Poor
A355: 45293 | B355: Manhattan | C355: Member | D355: Female | E355: Food & Beverages | F355: 14.23 | G355: 5 | H355: Credit card | I355: 4.4 | J355: 71.15 | K355: 3.5575 | L355: Poor
A356: 45293 | B356: Manhattan | C356: Member | D356: Male | E356: Sports & Travel | F356: 69.52 | G356: 7 | H356: Credit card | I356: 8.5 | J356: 486.64 | K356: 24.332 | L356: Good
A357: 45293 | B357: Queens | C357: Normal | D357: Female | E357: Electronics | F357: 23.07 | G357: 9 | H357: Cash | I357: 4.9 | J357: 207.63 | K357: 10.3815 | L357: Poor
A358: 45293 | B358: Queens | C358: Member | D358: Female | E358: Home & Lifestyle | F358: 80.79 | G358: 9 | H358: Credit card | I358: 9.5 | J358: 727.11 | K358: 36.3555 | L358: Good
A359: 45293 | B359: Manhattan | C359: Member | D359: Female | E359: Health & Beauty | F359: 77.68 | G359: 4 | H359: Cash | I359: 8.4 | J359: 310.72 | K359: 15.536 | L359: Good
A360: 45324 | B360: Brooklyn | C360: Member | D360: Female | E360: Electronics | F360: 26.26 | G360: 7 | H360: Cash | I360: 9.9 | J360: 183.82 | K360: 9.191 | L360: Good
A361: 45324 | B361: Manhattan | C361: Member | D361: Male | E361: Fashion & Accs | F361: 43.13 | G361: 10 | H361: Credit card | I361: 5.5 | J361: 431.3 | K361: 21.565 | L361: Poor
A362: 45324 | B362: Brooklyn | C362: Normal | D362: Female | E362: Fashion & Accs | F362: 25.56 | G362: 7 | H362: Cash | I362: 7.1 | J362: 178.92 | K362: 8.946 | L362: Average
A363: 45324 | B363: Queens | C363: Member | D363: Female | E363: Food & Beverages | F363: 38.42 | G363: 1 | H363: Cash | I363: 8.6 | J363: 38.42 | K363: 1.921 | L363: Good
A364: 45324 | B364: Queens | C364: Normal | D364: Male | E364: Food & Beverages | F364: 65.97 | G364: 8 | H364: Cash | I364: 8.4 | J364: 527.76 | K364: 26.388 | L364: Good
A365: 45324 | B365: Manhattan | C365: Member | D365: Female | E365: Sports & Travel | F365: 51.52 | G365: 8 | H365: Cash | I365: 9.6 | J365: 412.16 | K365: 20.608 | L365: Good
... A495: 45628 | B495: Manhattan | C495: Member | D495: Female | E495: Sports & Travel | F495: 71.63 | G495: 2 | H495: Ewallet | I495: 8.8 | J495: 143.26 | K495: 7.163 | L495: Good
B496: Manhattan | C496: Member | D496: Male | E496: Electronics | F496: 76.82 | G496: 1 | H496: Ewallet | I496: 7.2 | J496: 76.82 | K496: 3.841 | L496: Average
B497: Brooklyn | C497: Member | D497: Female | E497: Sports & Travel | F497: 20.18 | G497: 4 | H497: Credit card | I497: 5 | J497: 80.72 | K497: 4.036 | L497: Poor
B498: Queens | C498: Member | D498: Female | E498: Fashion & Accs | F498: 92.98 | G498: 2 | H498: Credit card | I498: 8 | J498: 185.96 | K498: 9.298 | L498: Good
B499: Brooklyn | C499: Member | D499: Female | E499: Fashion & Accs | F499: 29.56 | G499: 5 | H499: Cash | I499: 6.9 | J499: 147.8 | K499: 7.39 | L499: Average
B500: Queens | C500: Normal | D500: Female | E500: Fashion & Accs | F500: 22.51 | G500: 7 | H500: Credit card | I500: 4.8 | J500: 157.57 | K500: 7.8785 | L500: Poor
B501: Queens | C501: Member | D501: Female | E501: Food & Beverages | F501: 14.87 | G501: 2 | H501: Credit card | I501: 8.9 | J501: 29.74 | K501: 1.487 | L501: Good
B502: Manhattan | C502: Member | D502: Male | E502: Electronics | F502: 32.25 | G502: 4 | H502: Ewallet | I502: 6.5 | J502: 129 | K502: 6.45 | L502: Average
B503: Brooklyn | C503: Normal | D503: Male | E503: Sports & Travel | F503: 13.69 | G503: 6 | H503: Cash | I503: 6.3 | J503: 82.14 | K503: 4.107 | L503: Average
B504: Manhattan | C504: Member | D504: Male | E504: Health & Beauty | F504: 91.3 | G504: 1 | H504: Ewallet | I504: 9.2 | J504: 91.3 | K504: 4.565 | L504: Good
B505: Manhattan | C505: Normal | D505: Male | E505: Sports & Travel | F505: 44.65 | G505: 3 | H505: Cash | I505: 6.2 | J505: 133.95 | K505: 6.6975 | L505: Average
B506: Brooklyn | C506: Member | D506: Male | E506: Health & Beauty | F506: 75.74 | G506: 4 | H506: Cash | I506: 7.6 | J506: 302.96 | K506: 15.148 | L506: Average
B507: Brooklyn | C507: Member | D507: Female | E507: Sports & Travel | F507: 60.08 | G507: 7 | H507: Credit card | I507: 4.5 | J507: 420.56 | K507: 21.028 | L507: Poor
... B664: Manhattan | C664: Member | D664: Female | E664: Health & Beauty | F664: 10.16 | G664: 5 | H664: Ewallet | I664: 4.1 | J664: 50.8 | K664: 2.54 | L664: Poor
A665: 45294 | B665: Brooklyn | C665: Normal | D665: Male | E665: Electronics | F665: 27.5 | G665: 3 | H665: Ewallet | I665: 6.5 | J665: 82.5 | K665: 4.125 | L665: Average
A666: 45294 | B666: Queens | C666: Member | D666: Female | E666: Food & Beverages | F666: 74.89 | G666: 4 | H666: Ewallet | I666: 4.2 | J666: 299.56 | K666: 14.978 | L666: Poor
A667: 45294 | B667: Manhattan | C667: Normal | D667: Female | E667: Electronics | F667: 45.48 | G667: 10 | H667: Credit card | I667: 4.8 | J667: 454.8 | K667: 22.74 | L667: Poor
A668: 45294 | B668: Brooklyn | C668: Member | D668: Male | E668: Food & Beverages | F668: 53.72 | G668: 1 | H668: Ewallet | I668: 6.4 | J668: 53.72 | K668: 2.686 | L668: Average
A669: 45294 | B669: Brooklyn | C669: Member | D669: Male | E669: Fashion & Accs | F669: 81.31 | G669: 7 | H669: Ewallet | I669: 6.3 | J669: 569.17 | K669: 28.4585 | L669: Average
A670: 45294 | B670: Manhattan | C670: Normal | D670: Male | E670: Home & Lifestyle | F670: 34.73 | G670: 2 | H670: Ewallet | I670: 9.7 | J670: 69.46 | K670: 3.473 | L670: Good
A671: 45294 | B671: Queens | C671: Normal | D671: Male | E671: Fashion & Accs | F671: 78.55 | G671: 9 | H671: Cash | I671: 7.2 | J671: 706.95 | K671: 35.3475 | L671: Average
A672: 45294 | B672: Manhattan | C672: Member | D672: Female | E672: Fashion & Accs | F672: 22.32 | G672: 4 | H672: Credit card | I672: 4.4 | J672: 89.28 | K672: 4.464 | L672: Poor
A673: 45294 | B673: Brooklyn | C673: Normal | D673: Male | E673: Health & Beauty | F673: 69.51 | G673: 2 | H673: Ewallet | I673: 8.1 | J673: 139.02 | K673: 6.951 | L673: Good
A674: 45294 | B674: Brooklyn | C674: Normal | D674: Male | E674: Health & Beauty | F674: 14.82 | G674: 3 | H674: Credit card | I674: 8.7 | J674: 44.46 | K674: 2.223 | L674: Good
A675: 45325 | B675: Brooklyn | C675: Member | D675: Female | E675: Electronics | F675: 26.26 | G675: 3 | H675: Ewallet | I675: 6.3 | J675: 78.78 | K675: 3.939 | L675: Average
A676: 45325 | B676: Queens | C676: Member | D676: Female | E676: Sports & Travel | F676: 54.55 | G676: 10 | H676: Credit card | I676: 7.1 | J676: 545.5 | K676: 27.275 | L676: Average
... A817: 45629 | B817: Brooklyn | C817: Member | D817: Male | E817: Health & Beauty | F817: 39.01 | G817: 1 | H817: Credit card | I817: 4.7 | J817: 39.01 | K817: 1.9505 | L817: Poor
B818: Queens | C818: Normal | D818: Male | E818: Fashion & Accs | F818: 56.5 | G818: 1 | H818: Ewallet | I818: 9.6 | J818: 56.5 | K818: 2.825 | L818: Good
B819: Manhattan | C819: Normal | D819: Female | E819: Food & Beverages | F819: 54.27 | G819: 5 | H819: Ewallet | I819: 4.6 | J819: 271.35 | K819: 13.5675 | L819: Poor
B820: Brooklyn | C820: Member | D820: Female | E820: Fashion & Accs | F820: 38.3 | G820: 4 | H820: Cash | I820: 5.7 | J820: 153.2 | K820: 7.66 | L820: Poor
B821: Manhattan | C821: Member | D821: Male | E821: Health & Beauty | F821: 15.87 | G821: 10 | H821: Cash | I821: 5.8 | J821: 158.7 | K821: 7.935 | L821: Poor
B822: Manhattan | C822: Normal | D822: Male | E822: Food & Beverages | F822: 45.79 | G822: 7 | H822: Credit card | I822: 7 | J822: 320.53 | K822: 16.0265 | L822: Average
B823: Queens | C823: Member | D823: Male | E823: Sports & Travel | F823: 72.88 | G823: 2 | H823: Cash | I823: 6.1 | J823: 145.76 | K823: 7.288 | L823: Average
B824: Brooklyn | C824: Normal | D824: Male | E824: Health & Beauty | F824: 18.11 | G824: 10 | H824: Ewallet | I824: 5.9 | J824: 181.1 | K824: 9.055 | L824: Poor
B825: Brooklyn | C825: Normal | D825: Female | E825: Fashion & Accs | F825: 34.7 | G825: 2 | H825: Ewallet | I825: 8.2 | J825: 69.4 | K825: 3.47 | L825: Good
B826: Queens | C826: Member | D826: Male | E826: Home & Lifestyle | F826: 63.91 | G826: 8 | H826: Credit card | I826: 4.6 | J826: 511.28 | K826: 25.564 | L826: Poor
B827: Queens | C827: Normal | D827: Female | E827: Fashion & Accs | F827: 12.19 | G827: 8 | H827: Ewallet | I827: 6.8 | J827: 97.52 | K827: 4.876 | L827: Average
B828: Queens | C828: Normal | D828: Female | E828: Electronics | F828: 51.32 | G828: 9 | H828: Cash | I828: 5.6 | J828: 461.88 | K828: 23.094 | L828: Poor
B829: Queens | C829: Member | D829: Male | E829: Sports & Travel | F829: 42.85 | G829: 1 | H829: Credit card | I829: 9.3 | J829: 42.85 | K829: 2.1425 | L829: Good
... B1009: Queens | C1009: Normal | D1009: Male | E1009: Health & Beauty | F1009: 70.21 | G1009: 6 | H1009: Cash | I1009: 7.4 | J1009: 421.26 | K1009: 21.063 | L1009: Average
A1010: 45295 | B1010: Queens | C1010: Member | D1010: Male | E1010: Electronics | F1010: 37.06 | G1010: 4 | H1010: Ewallet | I1010: 9.7 | J1010: 148.24 | K1010: 7.412 | L1010: Good
A1011: 45295 | B1011: Brooklyn | C1011: Member | D1011: Male | E1011: Electronics | F1011: 87.87 | G1011: 9 | H1011: Ewallet | I1011: 5.6 | J1011: 790.83 | K1011: 39.5415 | L1011: Poor
A1012: 45295 | B1012: Brooklyn | C1012: Normal | D1012: Male | E1012: Electronics | F1012: 45.35 | G1012: 6 | H1012: Ewallet | I1012: 6.1 | J1012: 272.1 | K1012: 13.605 | L1012: Average
A1013: 45295 | B1013: Manhattan | C1013: Member | D1013: Male | E1013: Electronics | F1013: 66.35 | G1013: 1 | H1013: Credit card | I1013: 9.7 | J1013: 66.35 | K1013: 3.3175 | L1013: Good
A1014: 45295 | B1014: Queens | C1014: Member | D1014: Female | E1014: Food & Beverages | F1014: 87.48 | G1014: 6 | H1014: Ewallet | I1014: 5.1 | J1014: 524.88 | K1014: 26.244 | L1014: Poor
A1015: 45295 | B1015: Manhattan | C1015: Member | D1015: Female | E1015: Food & Beverages | F1015: 14.23 | G1015: 5 | H1015: Credit card | I1015: 4.4 | J1015: 71.15 | K1015: 3.5575 | L1015: Poor
A1016: 45295 | B1016: Queens | C1016: Normal | D1016: Female | E1016: Electronics | F1016: 23.07 | G1016: 9 | H1016: Cash | I1016: 4.9 | J1016: 207.63 | K1016: 10.3815 | L1016: Poor
A1017: 45295 | B1017: Queens | C1017: Member | D1017: Female | E1017: Home & Lifestyle | F1017: 80.79 | G1017: 9 | H1017: Credit card | I1017: 9.5 | J1017: 727.11 | K1017: 36.3555 | L1017: Good
A1018: 45295 | B1018: Brooklyn | C1018: Member | D1018: Female | E1018: Electronics | F1018: 26.26 | G1018: 7 | H1018: Cash | I1018: 9.9 | J1018: 183.82 | K1018: 9.191 | L1018: Good
A1019: 45295 | B1019: Queens | C1019: Normal | D1019: Female | E1019: Fashion & Accs | F1019: 62.18 | G1019: 10 | H1019: Ewallet | I1019: 6 | J1019: 621.8 | K1019: 31.09 | L1019: Average
A1020: 45295 | B1020: Brooklyn | C1020: Normal | D1020: Male | E1020: Fashion & Accs | F1020: 69.08 | G1020: 2 | H1020: Credit card | I1020: 6.9 | J1020: 138.16 | K1020: 6.908 | L1020: Average
A1021: 45295 | B1021: Manhattan | C1021: Member | D1021: Female | E1021: Health & Beauty | F1021: 77.68 | G1021: 4 | H1021: Cash | I1021: 8.4 | J1021: 310.72 | K1021: 15.536 | L1021: Good
... A1242: 45630 | B1242: Queens | C1242: Normal | D1242: Male | E1242: Health & Beauty | F1242: 70.21 | G1242: 6 | H1242: Cash | I1242: 7.4 | J1242: 421.26 | K1242: 21.063 | L1242: Average
B1243: Brooklyn | C1243: Normal | D1243: Male | E1243: Fashion & Accs | F1243: 69.08 | G1243: 2 | H1243: Credit card | I1243: 6.9 | J1243: 138.16 | K1243: 6.908 | L1243: Average
B1244: Brooklyn | C1244: Normal | D1244: Male | E1244: Electronics | F1244: 45.35 | G1244: 6 | H1244: Ewallet | I1244: 6.1 | J1244: 272.1 | K1244: 13.605 | L1244: Average
B1245: Manhattan | C1245: Member | D1245: Male | E1245: Electronics | F1245: 66.35 | G1245: 1 | H1245: Credit card | I1245: 9.7 | J1245: 66.35 | K1245: 3.3175 | L1245: Good
B1246: Queens | C1246: Member | D1246: Female | E1246: Food & Beverages | F1246: 87.48 | G1246: 6 | H1246: Ewallet | I1246: 5.1 | J1246: 524.88 | K1246: 26.244 | L1246: Poor
B1247: Manhattan | C1247: Member | D1247: Female | E1247: Food & Beverages | F1247: 14.23 | G1247: 5 | H1247: Credit card | I1247: 4.4 | J1247: 71.15 | K1247: 3.5575 | L1247: Poor
B1248: Manhattan | C1248: Member | D1248: Male | E1248: Sports & Travel | F1248: 69.52 | G1248: 7 | H1248: Credit card | I1248: 8.5 | J1248: 486.64 | K1248: 24.332 | L1248: Good
...

Sheet Data Analysis
A1: SUPERMARKET SALES DATA ANALYSIS
A3: 1. Which branch generates the highest total sales? | C3: BRANCH | D3: Total Sales | E3: No.of Sales | F3: Average Sales
C4: {=_xlfn.UNIQUE(Table2_1[Branch])} -> Brooklyn | D4: =SUMIF(Table2_1[Branch],$C4,Table2_1[Total sales]) -> 319705.48 | E4: =COUNTIF(Table2_1[Branch],$C4) -> 1793 | F4: =AVERAGEIF(Table2_1[Branch],$C4,Table2_1[Total sales]) -> 178.30757
C5: Queens | D5: =SUMIF(Table2_1[Branch],$C5,Table2_1[Total sales]) -> 312842.82 | E5: =COUNTIF(Table2_1[Branch],$C5) -> 1555 | F5: =AVERAGEIF(Table2_1[Branch],$C5,Table2_1[Total sales]) -> 201.18509
C6: Manhattan | D6: =SUMIF(Table2_1[Branch],$C6,Table2_1[Total sales]) -> 309996.55 | E6: =COUNTIF(Table2_1[Branch],$C6) -> 1705 | F6: =AVERAGEIF(Table2_1[Branch],$C6,Table2_1[Total sales]) -> 181.81616
A8: 2.Which product line generates the highest sales and sells the most quantity? | C8: Products | D8: Total Sales | E8: Total Quantity
C9: {=_xlfn.UNIQUE(Table2_1[Product line])} -> Food & Beverages | D9: =SUMIF(Table2_1[Product line],$C9,Table2_1[Total sales]) -> 151357.73 | E9: =SUMIF(Table2_1[Product line],$C9,Table2_1[Quantity]) -> 7309
C10: Electronics | D10: =SUMIF(Table2_1[Product line],$C10,Table2_1[Total sales]) -> 159259.1 | E10: =SUMIF(Table2_1[Product line],$C10,Table2_1[Quantity]) -> 2325
C11: Sports & Travel | D11: =SUMIF(Table2_1[Product line],$C11,Table2_1[Total sales]) -> 164252.94 | E11: =SUMIF(Table2_1[Product line],$C11,Table2_1[Quantity]) -> 2697
C12: Fashion & Accs | D12: =SUMIF(Table2_1[Product line],$C12,Table2_1[Total sales]) -> 101843.91 | E12: =SUMIF(Table2_1[Product line],$C12,Table2_1[Quantity]) -> 3123
C13: Home & Lifestyle | D13: =SUMIF(Table2_1[Product line],$C13,Table2_1[Total sales]) -> 197260.56 | E13: =SUMIF(Table2_1[Product line],$C13,Table2_1[Quantity]) -> 3461
C14: Health & Beauty | D14: =SUMIF(Table2_1[Product line],$C14,Table2_1[Total sales]) -> 168570.61 | E14: =SUMIF(Table2_1[Product line],$C14,Table2_1[Quantity]) -> 4296
A16: 3. How do Member and Normal customers differ in their spending? | C16: Customer type | D16: Total Sales | E16: No.of Sales | F16: Average Sales | G16: Total Quantity
C17: Member | D17: =SUMIF(Table2_1[Customer type],$C17,Table2_1[Total sales]) -> 436368.17 | E17: =COUNTIF(Table2_1[Customer type],$C17) -> 2085 | F17: =AVERAGEIF(Table2_1[Customer type],$C17,Table2_1[Total sales]) -> 209.28929 | G17: =SUMIF(Table2_1[Customer type],$C17,Table2_1[Quantity]) -> 10089
C18: Normal | D18: =SUMIF(Table2_1[Customer type],$C18,Table2_1[Total sales]) -> 506176.68 | E18: =COUNTIF(Table2_1[Customer type],$C18) -> 2968 | F18: =AVERAGEIF(Table2_1[Customer type],$C18,Table2_1[Total sales]) -> 170.5447 | G18: =SUMIF(Table2_1[Customer type],$C18,Table2_1[Quantity]) -> 13122
A20: 4. Which payment method is most commonly used and generates the highest sales? | C20: Payment Method | D20: Total Sales | E20: Payment count
C21: {=_xlfn.UNIQUE(Table2_1[Payment])} -> Credit card | D21: =SUMIF(Table2_1[Payment],'Data Analysis'!$C21,Table2_1[Total sales]) -> 311230.89 | E21: =COUNTIF(Table2_1[Payment],'Data Analysis'!$C21) -> 1594
C22: Cash | D22: =SUMIF(Table2_1[Payment],'Data Analysis'!$C22,Table2_1[Total sales]) -> 304622.65 | E22: =COUNTIF(Table2_1[Payment],'Data Analysis'!$C22) -> 1674
C23: Ewallet | D23: =SUMIF(Table2_1[Payment],'Data Analysis'!$C23,Table2_1[Total sales]) -> 326691.31 | E23: =COUNTIF(Table2_1[Payment],'Data Analysis'!$C23) -> 1785
A25: 5. Is customer rating related to sales performance? | C25: Rating Category | D25: No.of ratings | E25: Total Sales | F25: Average Sales | G25: Average Rating
C26: {=_xlfn.UNIQUE(Table2_1[Rating Category])} -> Good | D26: =COUNTIF(Table2_1[Rating Category],'Data Analysis'!$C26) -> 1529 | E26: =SUMIF(Table2_1[Rating Category],'Data Analysis'!$C26,Table2_1[Total sales]) -> 286422.23 | F26: =AVERAGEIF(Table2_1[Rating Category],'Data Analysis'!$C26,Table2_1[Total sales]) -> 187.32651 | G26: =AVERAGEIF(Table2_1[Rating Category],'Data Analysis'!$C26,Table2_1[Rating]) -> 8.8301504
C27: Average | D27: =COUNTIF(Table2_1[Rating Category],'Data Analysis'!$C27) -> 2043 | E27: =SUMIF(Table2_1[Rating Category],'Data Analysis'!$C27,Table2_1[Total sales]) -> 330894.46 | F27: =AVERAGEIF(Table2_1[Rating Category],'Data Analysis'!$C27,Table2_1[Total sales]) -> 161.96498 | G27: =AVERAGEIF(Table2_1[Rating Category],'Data Analysis'!$C27,Table2_1[Rating]) -> 6.9919236
C28: Poor | D28: =COUNTIF(Table2_1[Rating Category],'Data Analysis'!$C28) -> 1481 | E28: =SUMIF(Table2_1[Rating Category],'Data Analysis'!$C28,Table2_1[Total sales]) -> 325228.16 | F28: =AVERAGEIF(Table2_1[Rating Category],'Data Analysis'!$C28,Table2_1[Total sales]) -> 219.60038 | G28: =AVERAGEIF(Table2_1[Rating Category],'Data Analysis'!$C28,Table2_1[Rating]) -> 4.7259959

Sheet Questions
A1: SUPERMARKET SALES ANALYSIS
A2: No. | B2: Business Questions
A3: 1 | B3: Which branch generates the highest total sales?
A4: 2 | B4: Which product line generates the highest sales and sells the most quantity?
A5: 3 | B5: How do Member and Normal customers differ in their spending?
A6: 4 | B6: Which payment method is most commonly used and generates the highest sales?

Sheet DASHBOARD

Sheet INSIGHTS
E4: INSIGHTS | F4: RECOMMENDATIONS
E5: Brooklyn has the highest total sales at 319,705.48. | F5: Study Brooklyn's successful sales practices and apply them to other branches.
E6: Home & Lifestyle has the highest sales, while Food & Beverages has the highest quantity sold. | F6: Maintain Food & Beverages stock and promote Home & Lifestyle products.
E7: Members spend more per sale (209.29), while Normal customers generate higher total sales. | F7: Encourage Normal customers to join the membership program.
E8: Ewallet is the most used payment method and has the highest sales at 326,691.31. | F8: Continue supporting Ewallet and ensure reliable digital payments.
E9: Poor-rated sales have the highest average value (219.60), so higher ratings do not mean higher sales. | F9: Investigate reasons for poor ratings, especially on high-value purchases.

Sheet Changelog
G7: CHANGE MADE | H7: REASON
G8: Removed duplicate records | H8: To avoid duplicate sales data
G9: Corrected inconsistent text values | H9: To maintain consistent categories.
G10: Standardized column names | H10: To make the dataset clear and easy to analyze
G11: Checked and corrected data types | H11: To ensure values are suitable for analysis
G12: Added Tax Amount column | H12: To calculate the tax amount for each sale.
G13: Added Total Sales column | H13: To calculate the final sales amount including tax.
G14: Created Rating Category | H14: To group customer ratings into Good, Average, and Poor.
G15: Created PivotTables | H15: To summarize data and validate the analysis.
G16: Added formulas for business questions | H16: To provide data-driven answers.
G17: Added charts, slicers and KPI cards | H17: To create an interactive dashboard.

Sheet spark
A3: Row Labels | B3: Sum of Total sales
A4: <01-01-2024 | B4: 532465.92
A5: Jan | B5: 36420.88
A6: Feb | B6: 38399.9
A7: Mar | B7: 35443.64
A8: Apr | B8: 35878.12
A9: May | B9: 40137.64
A10: Jun | B10: 29753.03
A11: Jul | B11: 28843.67
A12: Aug | B12: 34056.65
A13: Sep | B13: 34642.57
A14: Oct | B14: 29701.94
A15: Nov | B15: 31112.91
... A17: Grand Total | B17: 942544.85

Sheet KPI
A3: Row Labels | B3: Sum of Total sales | C3: Sum of Quantity
A4: Electronics | B4: 159259.1 | C4: 2325
A5: Fashion & Accs | B5: 101843.91 | C5: 3123
A6: Food & Beverages | B6: 151357.73 | C6: 7309
A7: Health & Beauty | B7: 168570.61 | C7: 4296
A8: Home & Lifestyle | B8: 197260.56 | C8: 3461
A9: Sports & Travel | B9: 164252.94 | C9: 2697
A10: Grand Total | B10: 942544.85 | C10: 23211

Sheet Pivot_Branch
A3: Branch | B3: Sum of Total sales
A4: Brooklyn | B4: 319705.48
A5: Manhattan | B5: 309996.55
A6: Queens | B6: 312842.82
A7: Grand Total | B7: 942544.85

Sheet Pivot_Product
A3: Product | B3: Sum of Total sales | C3: Sum of Quantity
A4: Electronics | B4: 159259.1 | C4: 2325
A5: Fashion & Accs | B5: 101843.91 | C5: 3123
A6: Food & Beverages | B6: 151357.73 | C6: 7309
A7: Health & Beauty | B7: 168570.61 | C7: 4296
A8: Home & Lifestyle | B8: 197260.56 | C8: 3461
A9: Sports & Travel | B9: 164252.94 | C9: 2697
A10: Grand Total | B10: 942544.85 | C10: 23211

Sheet Pivot_customer
A3: Customer | B3: Sum of Total sales
A4: Member | B4: 436368.17
A5: Normal | B5: 506176.68
A6: Grand Total | B6: 942544.85

Sheet Pivot_Payment
A3: Payment method | B3: Count of Payment
A4: Cash | B4: 1674
A5: Credit card | B5: 1594
A6: Ewallet | B6: 1785
A7: Grand Total | B7: 5053

Sheet Pivot_Rating
A3: Rating
A4: Good
A5: Grand Total
